nextcloud/__init__.py
nextcloud/base.py
nextcloud/codes.py
nextcloud/compat.py
nextcloud/exceptions.py
nextcloud/requester.py
nextcloud/response.py
nextcloud/session.py
nextcloud/api/__init__.py
nextcloud/api/item_set.py
nextcloud/api/model.py
nextcloud/api/properties.py
nextcloud/api_wrappers/__init__.py
nextcloud/api_wrappers/activity.py
nextcloud/api_wrappers/apps.py
nextcloud/api_wrappers/capabilities.py
nextcloud/api_wrappers/federated_cloudshares.py
nextcloud/api_wrappers/group.py
nextcloud/api_wrappers/group_folders.py
nextcloud/api_wrappers/notifications.py
nextcloud/api_wrappers/share.py
nextcloud/api_wrappers/systemtags.py
nextcloud/api_wrappers/user.py
nextcloud/api_wrappers/user_ldap.py
nextcloud/api_wrappers/webdav.py
nextcloud/common/__init__.py
nextcloud/common/build_xml.py
nextcloud/common/namming.py
nextcloud/common/parse_xml.py
nextcloud/common/paths.py
nextcloud/common/timestamping.py
nextcloud/models/__init__.py
nextcloud_api_wrapper-0.2.3.dist-info/AUTHORS.rst
nextcloud_api_wrapper-0.2.3.dist-info/LICENSE
nextcloud_api_wrapper-0.2.3.dist-info/METADATA
nextcloud_api_wrapper-0.2.3.dist-info/WHEEL
nextcloud_api_wrapper-0.2.3.dist-info/top_level.txt
nextcloud_api_wrapper-0.2.3.dist-info/RECORD
