Metadata-Version: 2.1
Name: nextcloud-api-wrapper
Version: 0.2.3
Summary: Python wrapper for NextCloud api
Home-page: UNKNOWN
Author: Luffah
Author-email: luffah@runbox.com
License: GPLv3
Project-URL: Source, https://github.com/luffah/nextcloud-API
Keywords: requests,api,wrapper,nextcloud,owncloud
Platform: any
Classifier: Programming Language :: Python
Classifier: Programming Language :: Python :: 2
Classifier: Programming Language :: Python :: 3
Classifier: Development Status :: 4 - Beta
Classifier: Environment :: Web Environment
Classifier: Intended Audience :: Developers
Classifier: Topic :: Internet :: WWW/HTTP
Classifier: Topic :: Software Development :: Libraries :: Python Modules
Classifier: License :: OSI Approved :: GNU General Public License (GPL)
Classifier: Operating System :: OS Independent
Provides-Extra: tests
